Library/SortOfFigs.py
Library/__init__.py
SortOfFigs-0.0.8.dist-info/LICENSE
SortOfFigs-0.0.8.dist-info/METADATA
SortOfFigs-0.0.8.dist-info/WHEEL
SortOfFigs-0.0.8.dist-info/top_level.txt
SortOfFigs-0.0.8.dist-info/RECORD
